dfrobot_id809/__init__.py
dfrobot_id809/base.py
dfrobot_id809/constants.py
dfrobot_id809/errors.py
dfrobot_id809/i2c.py
dfrobot_id809/led.py
dfrobot_id809/py.typed
sen0359-0.1.0.dist-info/licenses/LICENSE
sen0359-0.1.0.dist-info/METADATA
sen0359-0.1.0.dist-info/WHEEL
sen0359-0.1.0.dist-info/top_level.txt
sen0359-0.1.0.dist-info/RECORD
