Metadata-Version: 2.4
Name: SEN0359
Version: 0.1.0
Summary: MicroPython driver for DFRobot SEN0359 ID809 capacitive fingerprint sensor
Author: Fariiixm
Maintainer: Fariiixm
License-Expression: MIT
Project-URL: Homepage, https://github.com/Fariiixm/SEN0359
Project-URL: Documentation, https://github.com/Fariiixm/SEN0359#readme
Project-URL: Repository, https://github.com/Fariiixm/SEN0359.git
Project-URL: Issues, https://github.com/Fariiixm/SEN0359/issues
Keywords: micropython,dfrobot,fingerprint,sensor,id809,sen0359,biometric,i2c,embedded
Classifier: Development Status :: 4 - Beta
Classifier: Intended Audience :: Developers
Classifier: Operating System :: OS Independent
Classifier: Programming Language :: Python :: 3
Classifier: Programming Language :: Python :: 3.7
Classifier: Programming Language :: Python :: 3.8
Classifier: Programming Language :: Python :: 3.9
Classifier: Programming Language :: Python :: 3.10
Classifier: Programming Language :: Python :: 3.11
Classifier: Programming Language :: Python :: 3.12
Classifier: Programming Language :: Python :: Implementation :: MicroPython
Classifier: Topic :: Software Development :: Embedded Systems
Classifier: Topic :: System :: Hardware :: Hardware Drivers
Requires-Python: >=3.7
License-File: LICENSE
Provides-Extra: dev
Requires-Dist: micropython-rp2-stubs; extra == "dev"
Requires-Dist: pytest>=7.0; extra == "dev"
Requires-Dist: ruff>=0.1.0; extra == "dev"
Provides-Extra: stubs-esp32
Requires-Dist: micropython-esp32-stubs; extra == "stubs-esp32"
Provides-Extra: stubs-rp2
Requires-Dist: micropython-rp2-stubs; extra == "stubs-rp2"
Provides-Extra: stubs-stm32
Requires-Dist: micropython-stm32-stubs; extra == "stubs-stm32"
Dynamic: license-file
